odoo/addons/partner_category_security_crm/README.rst
odoo/addons/partner_category_security_crm/__init__.py
odoo/addons/partner_category_security_crm/__manifest__.py
odoo/addons/partner_category_security_crm/i18n/es.po
odoo/addons/partner_category_security_crm/i18n/it.po
odoo/addons/partner_category_security_crm/i18n/partner_category_security_crm.pot
odoo/addons/partner_category_security_crm/readme/CONTRIBUTORS.rst
odoo/addons/partner_category_security_crm/readme/DESCRIPTION.rst
odoo/addons/partner_category_security_crm/readme/USAGE.rst
odoo/addons/partner_category_security_crm/security/ir.model.access.csv
odoo/addons/partner_category_security_crm/static/description/icon.png
odoo/addons/partner_category_security_crm/static/description/index.html
odoo/addons/partner_category_security_crm/tests/__init__.py
odoo/addons/partner_category_security_crm/tests/test_partner_category_security_crm.py
odoo_addon_partner_category_security_crm-16.0.1.0.0.3.dist-info/METADATA
odoo_addon_partner_category_security_crm-16.0.1.0.0.3.dist-info/WHEEL
odoo_addon_partner_category_security_crm-16.0.1.0.0.3.dist-info/top_level.txt
odoo_addon_partner_category_security_crm-16.0.1.0.0.3.dist-info/RECORD
